.gitignore
CHANGES.rst
LICENSE.txt
MANIFEST.in
README.rst
bootstrap.py
buildout.cfg
setup.py
js/__init__.py
js.blocksit.egg-info/PKG-INFO
js.blocksit.egg-info/SOURCES.txt
js.blocksit.egg-info/dependency_links.txt
js.blocksit.egg-info/entry_points.txt
js.blocksit.egg-info/namespace_packages.txt
js.blocksit.egg-info/not-zip-safe
js.blocksit.egg-info/requires.txt
js.blocksit.egg-info/top_level.txt
js/blocksit/__init__.py
js/blocksit/test_blocksit.rst
js/blocksit/resources/bg.gif
js/blocksit/resources/blocksit.js
js/blocksit/resources/blocksit.min.js
js/blocksit/resources/index.html
js/blocksit/resources/style.css
js/blocksit/resources/demo1/index.html
js/blocksit/resources/demo1/style.css
js/blocksit/resources/demo2/index.html
js/blocksit/resources/demo2/style.css
js/blocksit/resources/font/distgrg_-webfont.eot
js/blocksit/resources/font/distgrg_-webfont.svg
js/blocksit/resources/font/distgrg_-webfont.ttf
js/blocksit/resources/font/distgrg_-webfont.woff