Metadata-Version: 1.0
Name: js.blocksit
Version: 1.0
Summary: fanstatic blocksit jQuery.
Home-page: UNKNOWN
Author: Lugensa GmbH
Author-email: jd@lugensa.com
License: BSD
Platform: UNKNOWN
